SklTransformer/SKTransformer.py
SklTransformer/__init__.py
SklTransformer/call.py
SklTransformer/matrix.py
SklTransformer/tuning.py
SklTransformer-0.4.dist-info/METADATA
SklTransformer-0.4.dist-info/WHEEL
SklTransformer-0.4.dist-info/top_level.txt
SklTransformer-0.4.dist-info/RECORD
